[{"Name":"LoveCrafts Ukraine","Vacancies":[{"PositionName":"BACKEND ENGINEER, C#/INRIVER","Url":"https://jobs.dou.ua/companies/lovecrafts/vacancies/53103/?from=list_hot","Tags":["TDD"]}]},{"Name":"Flying Beagle Limited","Vacancies":[]},{"Name":"Rails Reactor","Vacancies":[{"PositionName":".NET CORE ENGINEER","Url":"https://jobs.dou.ua/companies/rails-reactor/vacancies/54652/?from=list_hot","Tags":[".Net Core","ASP.NET Web API"]}]},{"Name":"DataArt","Vacancies":[{"PositionName":"SENIOR .NET ENGINEER, SHIPPING SYSTEM","Url":"https://jobs.dou.ua/companies/dataart/vacancies/54225/?from=list_hot","Tags":["SPA(Single Page Application)",".Net Core","ASP.NET Web API","ASP.NET MVC","AngularJS"]}]},{"Name":"Levi9 Ukraine","Vacancies":[{"PositionName":"SENIOR .NET DEVELOPER","Url":"https://jobs.dou.ua/companies/levi9/vacancies/47619/?from=list_hot","Tags":["microservices","CQRS"]},{"PositionName":"JUNIOR .NET DEVELOPER","Url":"https://jobs.dou.ua/companies/levi9/vacancies/43960/","Tags":["microservices"]}]},{"Name":"PreciseQ","Vacancies":[{"PositionName":"SENIOR/MIDDLE FULL STACK DEVELOPER","Url":"https://jobs.dou.ua/companies/preciseq/vacancies/23360/?from=list_hot","Tags":["ASP.NET MVC","AngularJS"]}]},{"Name":"Altium Limited","Vacancies":[{"PositionName":"RND TEAM LEAD (C#) — KIEV","Url":"https://jobs.dou.ua/companies/altium-limited/vacancies/33890/","Tags":["ASP.NET MVC"]},{"PositionName":"FULL-STACK SENIOR C# ENGINEER (KIEV, R&AMP;D)","Url":"https://jobs.dou.ua/companies/altium-limited/vacancies/33893/","Tags":["SOLID","ASP.NET MVC"]}]},{"Name":"Glorium Technologies","Vacancies":[{"PositionName":"MIDDLE .NET DEVELOPER","Url":"https://jobs.dou.ua/companies/glorium-technologies-corp/vacancies/53303/","Tags":["Design Patterns","SOLID",".Net Core","ASP.NET Web API"]}]},{"Name":"Daxx BV","Vacancies":[{"PositionName":"FULL-STACK .NET TECH LEAD","Url":"https://jobs.dou.ua/companies/daxx-group/vacancies/53316/","Tags":[".Net Core","ASP.NET MVC"]},{"PositionName":"ASP.NET DEVELOPER","Url":"https://jobs.dou.ua/companies/daxx-group/vacancies/53673/","Tags":["ASP.NET MVC","AngularJS"]}]},{"Name":"Rontar","Vacancies":[{"PositionName":".NET / C# DEVELOPER","Url":"https://jobs.dou.ua/companies/sistema-upravleniya-reklamoj-rontar/vacancies/55074/","Tags":["ASP.NET Web API","ASP.NET MVC"]},{"PositionName":".NET / C# DEVELOPER","Url":"https://jobs.dou.ua/companies/sistema-upravleniya-reklamoj-rontar/vacancies/54103/","Tags":["ASP.NET Web API","ASP.NET MVC"]}]},{"Name":"IPLAND","Vacancies":[]},{"Name":"3Shape Ukraine","Vacancies":[{"PositionName":"C# SOFTWARE DEVELOPER","Url":"https://jobs.dou.ua/companies/3shape-ukraine/vacancies/55073/","Tags":["Design Patterns","TDD","SOLID"]},{"PositionName":"SENIOR .NET WEB DEVELOPER","Url":"https://jobs.dou.ua/companies/3shape-ukraine/vacancies/52892/","Tags":["Design Patterns","TDD","SOLID","ASP.NET Web API","ASP.NET MVC","AngularJS"]},{"PositionName":"SENIOR SITECORE .NET DEVELOPER","Url":"https://jobs.dou.ua/companies/3shape-ukraine/vacancies/39253/","Tags":["SOLID","ASP.NET MVC"]}]},{"Name":"SimCorp","Vacancies":[{"PositionName":"EXPERIENCED C# DEVELOPER (ENG)","Url":"https://jobs.dou.ua/companies/simcorp/vacancies/46246/","Tags":["SOLID"]}]},{"Name":"Serious Cake","Vacancies":[]},{"Name":"Ciklum","Vacancies":[{"PositionName":".NET DEVELOPER FOR KEY TRAVEL (KYIV)","Url":"https://jobs.dou.ua/companies/ciklum/vacancies/52986/","Tags":["Design Patterns",".Net Core","AngularJS","ReactJS"]},{"PositionName":"MIDDLE .NET DEVELOPER FOR SBTECH RETAIL UNIT (KYIV)","Url":"https://jobs.dou.ua/companies/ciklum/vacancies/50137/","Tags":["Design Patterns","SPA(Single Page Application)","SOLID","TypeScript","ReactJS"]},{"PositionName":"SENIOR C#/F#/.NET DEVELOPER FOR SBTECH ONLINE UNIT (KYIV)","Url":"https://jobs.dou.ua/companies/ciklum/vacancies/44195/","Tags":["Design Patterns","microservices","CQRS","TDD",".Net Core"]},{"PositionName":"SENIOR .NET DEVELOPER FOR TOBII PRO (KYIV)","Url":"https://jobs.dou.ua/companies/ciklum/vacancies/54284/","Tags":["TDD","SOLID"]},{"PositionName":"SENIOR .NET SOFTWARE ENGINEER FOR JUST EAT (KYIV)","Url":"https://jobs.dou.ua/companies/ciklum/vacancies/50311/","Tags":["ASP.NET Web API"]},{"PositionName":"SENIOR .NET DEVELOPER (FULL STACK) FOR BETSSON GROUP (KYIV)","Url":"https://jobs.dou.ua/companies/ciklum/vacancies/48527/","Tags":["ASP.NET MVC"]},{"PositionName":"SENIOR .NET DEVELOPER FOR QUALIWARE (KYIV)","Url":"https://jobs.dou.ua/companies/ciklum/vacancies/47580/","Tags":["Design Patterns"]},{"PositionName":"BACK END DEVELOPER FOR CIKLUM CLIENT (KYIV)","Url":"https://jobs.dou.ua/companies/ciklum/vacancies/54095/","Tags":["microservices","SOLID"]},{"PositionName":"SENIOR .NET DEVELOPER FOR CIKLUM CLIENT (KYIV)","Url":"https://jobs.dou.ua/companies/ciklum/vacancies/54071/","Tags":["Design Patterns","microservices","TDD","SOLID","ASP.NET Web API"]},{"PositionName":".NET SOFTWARE ENGINEER FOR JUST EAT (KYIV)","Url":"https://jobs.dou.ua/companies/ciklum/vacancies/54049/","Tags":["ASP.NET Web API"]},{"PositionName":"SENIOR WEB APPLICATION DEVELOPER FOR PAYONEER (KYIV)","Url":"https://jobs.dou.ua/companies/ciklum/vacancies/53714/","Tags":["ASP.NET MVC","AngularJS"]}]},{"Name":"BETLAB","Vacancies":[{"PositionName":"SENIOR .NET DEVELOPER FOR LIVE TEAM","Url":"https://jobs.dou.ua/companies/betlab/vacancies/54973/","Tags":["SOLID","AngularJS"]},{"PositionName":"SENIOR .NET DEVELOPER FOR MATH TEAM","Url":"https://jobs.dou.ua/companies/betlab/vacancies/54933/","Tags":["Design Patterns","microservices","TypeScript"]},{"PositionName":"SENIOR .NET DEVELOPER FOR CORE TEAM","Url":"https://jobs.dou.ua/companies/betlab/vacancies/54537/","Tags":["microservices",".Net Core","ASP.NET Web API"]}]},{"Name":"Infopulse","Vacancies":[]},{"Name":"iLogos","Vacancies":[]},{"Name":"NullGravity","Vacancies":[{"PositionName":"SENIOR .NET DEVELOPER","Url":"https://jobs.dou.ua/companies/null-gravity/vacancies/52786/","Tags":["Design Patterns",".Net Core","ASP.NET Web API"]}]},{"Name":"Trinetix","Vacancies":[{"PositionName":"SENIOR .NET DEVELOPER","Url":"https://jobs.dou.ua/companies/trinetix/vacancies/14712/","Tags":["TDD","ASP.NET Web API"]}]},{"Name":"LADevelopers Inc.","Vacancies":[]},{"Name":"Jooble","Vacancies":[{"PositionName":".NET DEVELOPER","Url":"https://jobs.dou.ua/companies/jooble/vacancies/38859/","Tags":["ASP.NET MVC"]}]},{"Name":"CoreValue","Vacancies":[{"PositionName":"MIDDLE .NET DEVELOPER","Url":"https://jobs.dou.ua/companies/corevalue/vacancies/54900/","Tags":["ASP.NET MVC"]}]},{"Name":"Terrasoft","Vacancies":[{"PositionName":"FULL-STACK C#/JAVASCRIPT DEVELOPER","Url":"https://jobs.dou.ua/companies/terrasoft/vacancies/52633/","Tags":["TDD"]},{"PositionName":"C#/.NET DEVELOPER","Url":"https://jobs.dou.ua/companies/terrasoft/vacancies/52634/","Tags":["TDD","ASP.NET Web API","ASP.NET MVC"]}]},{"Name":"Axon Development Group","Vacancies":[{"PositionName":".NET DEVELOPER","Url":"https://jobs.dou.ua/companies/axon-development-group/vacancies/54881/","Tags":["ASP.NET MVC"]}]},{"Name":"UNITY-BARS","Vacancies":[{"PositionName":".NET DEVELOPER","Url":"https://jobs.dou.ua/companies/unity-bars/vacancies/34879/","Tags":["ASP.NET MVC","AngularJS"]}]},{"Name":"Melior Games","Vacancies":[{"PositionName":"SENIOR ASP.NET MVC DEVELOPER","Url":"https://jobs.dou.ua/companies/melior-games/vacancies/2817/","Tags":["ASP.NET MVC","AngularJS"]}]},{"Name":"AllStars-IT Ukraine","Vacancies":[{"PositionName":"JB-106 FULL STACK JS TEAM LEADER","Url":"https://jobs.dou.ua/companies/allstars-it/vacancies/52733/","Tags":["RESTful API","SPA(Single Page Application)","TypeScript","AngularJS"]},{"PositionName":"JB-102 .NET TEAM LEADER (SERVER SIDE)","Url":"https://jobs.dou.ua/companies/allstars-it/vacancies/51233/","Tags":["SOLID"]},{"PositionName":"JB-101 .NET FULL STACK DEVELOPER","Url":"https://jobs.dou.ua/companies/allstars-it/vacancies/53376/","Tags":["TypeScript","AngularJS"]}]},{"Name":"SoftClub","Vacancies":[{"PositionName":"MIDDLE FULL STACK (C#+JAVASCRIPT) DEVELOPER","Url":"https://jobs.dou.ua/companies/softclub/vacancies/42147/","Tags":["ASP.NET Web API"]}]},{"Name":"Grammarly","Vacancies":[{"PositionName":"SOFTWARE ENGINEER, .NET","Url":"https://jobs.dou.ua/companies/grammarly/vacancies/44850/","Tags":["SOLID","TypeScript"]}]},{"Name":"Raiffeisen Bank Aval","Vacancies":[]},{"Name":"Newgistics","Vacancies":[{"PositionName":"SENIOR FULL STACK DEVELOPER (.NET)","Url":"https://jobs.dou.ua/companies/newgistics/vacancies/54687/","Tags":[".Net Core"]},{"PositionName":"SENIOR .NET DEVELOPER (DATA TEAM)","Url":"https://jobs.dou.ua/companies/newgistics/vacancies/47210/","Tags":[".Net Core"]}]},{"Name":"Lohika","Vacancies":[{"PositionName":"SENIOR C#/.NET SW ENGINEER","Url":"https://jobs.dou.ua/companies/lohika-systems/vacancies/11518/","Tags":["ASP.NET MVC"]}]},{"Name":"StarWind®","Vacancies":[{"PositionName":"C# DEVELOPER","Url":"https://jobs.dou.ua/companies/starwind/vacancies/17730/","Tags":["Design Patterns"]}]},{"Name":"CloudRoute, LLC","Vacancies":[{"PositionName":"JUNIOR .NET ENGINEER","Url":"https://jobs.dou.ua/companies/cloudroute/vacancies/54619/","Tags":["microservices","CQRS","SOLID",".Net Core","ASP.NET Web API"]},{"PositionName":"MIDDLE .NET ENGINEER","Url":"https://jobs.dou.ua/companies/cloudroute/vacancies/44133/","Tags":["microservices","CQRS","SOLID",".Net Core","ASP.NET Web API"]}]},{"Name":"Artificial Core","Vacancies":[{"PositionName":".NET DEVELOPER","Url":"https://jobs.dou.ua/companies/artificial-core/vacancies/44536/","Tags":["Design Patterns","ASP.NET Web API","ASP.NET MVC"]}]},{"Name":"Maxitech Software","Vacancies":[{"PositionName":"SENIOR BACKEND .NET DEVELOPER","Url":"https://jobs.dou.ua/companies/maxitech/vacancies/42353/","Tags":["SOLID",".Net Core","ReactJS"]}]},{"Name":"Room 8 Studio","Vacancies":[]},{"Name":"Invisible","Vacancies":[]},{"Name":"rabota.ua","Vacancies":[{"PositionName":"SENIOR .NET DEVELOPER","Url":"https://jobs.dou.ua/companies/rabota-ua/vacancies/50666/","Tags":["TDD","SOLID",".Net Core","ASP.NET MVC","AngularJS"]}]},{"Name":"KPMG","Vacancies":[{"PositionName":"JUNIOR .NET DEVELOPER","Url":"https://jobs.dou.ua/companies/kpmg/vacancies/54552/","Tags":["ASP.NET Web API","ASP.NET MVC","TypeScript","AngularJS"]},{"PositionName":"MIDDLE .NET DEVELOPER","Url":"https://jobs.dou.ua/companies/kpmg/vacancies/54550/","Tags":["SOLID","ASP.NET Web API","ASP.NET MVC","TypeScript","AngularJS"]}]},{"Name":"Macphun Software","Vacancies":[]},{"Name":"Digicode","Vacancies":[{"PositionName":"FULL-STACK .NET DEVELOPER","Url":"https://jobs.dou.ua/companies/digicode/vacancies/54502/","Tags":["RESTful API","ASP.NET Web API","ASP.NET MVC","AngularJS"]}]},{"Name":"Virtuace Inc","Vacancies":[{"PositionName":"WEB DEVELOPER WITH TRIDION SDL EXPERIENCE","Url":"https://jobs.dou.ua/companies/virtuace-inc/vacancies/54413/","Tags":["ASP.NET MVC"]},{"PositionName":"FULL STACK .NET DEVELOPER","Url":"https://jobs.dou.ua/companies/virtuace-inc/vacancies/49811/","Tags":["ASP.NET MVC"]}]},{"Name":"Valtech","Vacancies":[{"PositionName":"MIDDLE / SENIOR .NET DEVELOPER","Url":"https://jobs.dou.ua/companies/valtech/vacancies/54409/","Tags":["ASP.NET MVC"]}]},{"Name":"Playtech","Vacancies":[{"PositionName":"SENIOR .NET DEVELOPER","Url":"https://jobs.dou.ua/companies/playtech/vacancies/54390/","Tags":["ASP.NET Web API","ASP.NET MVC","TypeScript","AngularJS"]}]},{"Name":"Brain agency","Vacancies":[{"PositionName":"SENIOR .NET DEVELOPER","Url":"https://jobs.dou.ua/companies/brain-agency/vacancies/42331/","Tags":["RESTful API","SOLID",".Net Core","ASP.NET MVC"]}]},{"Name":"Materialise","Vacancies":[{"PositionName":"С#/С++ SOFTWARE ENGINEER (BP)","Url":"https://jobs.dou.ua/companies/materialise/vacancies/50203/","Tags":["Design Patterns","SOLID"]}]},{"Name":"Innovecs","Vacancies":[{"PositionName":"MIDDLE QA AUTOMATION (C#)","Url":"https://jobs.dou.ua/companies/innovecs/vacancies/52320/","Tags":["SOLID"]}]},{"Name":"iDeals Solutions","Vacancies":[{"PositionName":"MIDDLE .NET DEVELOPER","Url":"https://jobs.dou.ua/companies/ideals-solutions/vacancies/54295/","Tags":["Design Patterns","ASP.NET Web API"]},{"PositionName":"SENIOR .NET DEVELOPER","Url":"https://jobs.dou.ua/companies/ideals-solutions/vacancies/54089/","Tags":["Design Patterns","ASP.NET Web API"]},{"PositionName":"JUNIOR .NET DEVELOPER","Url":"https://jobs.dou.ua/companies/ideals-solutions/vacancies/50698/","Tags":["Design Patterns","ASP.NET Web API"]}]},{"Name":"Ring Ukraine","Vacancies":[{"PositionName":"C# UWP DEVELOPER","Url":"https://jobs.dou.ua/companies/ring-ukraine/vacancies/50336/","Tags":["Design Patterns","SOLID"]}]},{"Name":"Open Soft, LLC","Vacancies":[]},{"Name":"AIR (Agency of Internet Rights)","Vacancies":[{"PositionName":"SENIOR .NET DEVELOPER","Url":"https://jobs.dou.ua/companies/agency-of-internet-rights/vacancies/25442/","Tags":["RESTful API"]}]},{"Name":"Fareportal","Vacancies":[{"PositionName":"SENIOR .NET SOFTWARE ENGINEER (FINTECH)","Url":"https://jobs.dou.ua/companies/fareportal-r-and-d-center-in-ukraine/vacancies/49816/","Tags":[".Net Core","ASP.NET MVC"]}]},{"Name":"Speak With A Geek","Vacancies":[{"PositionName":"MIDDLE .NET ENGINEER","Url":"https://jobs.dou.ua/companies/speak-with-a-geek/vacancies/48166/","Tags":["SOLID",".Net Core","ASP.NET MVC"]}]},{"Name":"DB BEST Technologies","Vacancies":[]},{"Name":"B2B Soft","Vacancies":[{"PositionName":"SENIOR C# WEB DEVELOPER","Url":"https://jobs.dou.ua/companies/b2b-soft/vacancies/38310/","Tags":["Design Patterns","SPA(Single Page Application)","ASP.NET Web API","ASP.NET MVC"]},{"PositionName":"SENIOR/MIDDLE C# DEVELOPER","Url":"https://jobs.dou.ua/companies/b2b-soft/vacancies/53935/","Tags":["RESTful API","SOLID"]}]},{"Name":"ANIMO","Vacancies":[{"PositionName":"BACKEND DEVELOPER (.NET)","Url":"https://jobs.dou.ua/companies/animo/vacancies/49783/","Tags":["ASP.NET MVC"]}]},{"Name":"Wirex Ltd","Vacancies":[{"PositionName":"MIDDLE .NET DEVELOPER","Url":"https://jobs.dou.ua/companies/wirex-ltd/vacancies/53946/","Tags":["Design Patterns","CQRS","SOLID"]},{"PositionName":"SENIOR .NET BACKEND DEVELOPER","Url":"https://jobs.dou.ua/companies/wirex-ltd/vacancies/36241/","Tags":["RESTful API","SOLID","ASP.NET Web API"]}]},{"Name":"EPAM","Vacancies":[{"PositionName":"SENIOR .NET FULL STACK SOFTWARE ENGINEER (KYIV)","Url":"https://jobs.dou.ua/companies/epam-systems/vacancies/51803/","Tags":["Design Patterns","CQRS","TDD","SOLID",".Net Core","ASP.NET Web API","ASP.NET MVC","AngularJS","ReactJS"]},{"PositionName":"SENIOR FULL-STACK .NET SOFTWARE ENGINEER (KYIV)","Url":"https://jobs.dou.ua/companies/epam-systems/vacancies/53934/","Tags":["Design Patterns","TDD",".Net Core","ASP.NET Web API","ASP.NET MVC","AngularJS"]}]},{"Name":"Си Пи Ай - Киев, ТОВ","Vacancies":[]},{"Name":"CNW","Vacancies":[]},{"Name":"Uklon","Vacancies":[]},{"Name":"Quadrox","Vacancies":[{"PositionName":"JUNIOR C#/ASP.NET DEVELOPER","Url":"https://jobs.dou.ua/companies/quadrox/vacancies/28464/","Tags":["SPA(Single Page Application)","ASP.NET MVC"]}]},{"Name":"Intetics Inc.","Vacancies":[{"PositionName":"SENIOR FULLSTACK DEVELOPER (.NET+JS)","Url":"https://jobs.dou.ua/companies/intetics-co/vacancies/49752/","Tags":["SPA(Single Page Application)","ASP.NET MVC","AngularJS"]}]},{"Name":"IT-Solutions","Vacancies":[]},{"Name":"Edenlab","Vacancies":[]},{"Name":"Rozetka.ua  интернет-супермаркет","Vacancies":[{"PositionName":"C# DEVELOPER","Url":"https://jobs.dou.ua/companies/rozetka-ua-internet-supermarket/vacancies/51696/","Tags":["RESTful API","ASP.NET MVC"]}]},{"Name":"Intellectsoft","Vacancies":[{"PositionName":"FULL-STACK DEVELOPER (.NET AND ANGULAR 2)","Url":"https://jobs.dou.ua/companies/intellectsoft/vacancies/53713/","Tags":["microservices","AngularJS"]}]},{"Name":"Boovatech","Vacancies":[{"PositionName":"FULL-STACK WEB DEVELOPER (SPA + .NET)","Url":"https://jobs.dou.ua/companies/boovatech/vacancies/37204/","Tags":["Design Patterns","SPA(Single Page Application)","AngularJS","ReactJS"]}]},{"Name":"EGO creative media solutions","Vacancies":[{"PositionName":"MIDDLE .NET/ANGULAR.JS DEVELOPER","Url":"https://jobs.dou.ua/companies/ego-cms/vacancies/11512/","Tags":[".Net Core","TypeScript","AngularJS"]}]},{"Name":"N-iX","Vacancies":[{"PositionName":"SENIOR .NET BACK END DEVELOPER","Url":"https://jobs.dou.ua/companies/n-ix/vacancies/53633/","Tags":["ASP.NET Web API"]}]},{"Name":"Itera","Vacancies":[{"PositionName":"SENIOR .NET DEVELOPER","Url":"https://jobs.dou.ua/companies/itera-consulting-group-ukraine/vacancies/53608/","Tags":["ASP.NET MVC"]}]},{"Name":"Playtika UA","Vacancies":[{"PositionName":"MOBILE .NET TECHNICAL LEAD","Url":"https://jobs.dou.ua/companies/playtika-ua/vacancies/53605/","Tags":["TDD"]},{"PositionName":"SENIOR MOBILE .NET DEVELOPER","Url":"https://jobs.dou.ua/companies/playtika-ua/vacancies/53604/","Tags":["TDD"]}]},{"Name":"BANK PUMB (FUIB)","Vacancies":[{"PositionName":"SENIOR .NET DEVELOPER","Url":"https://jobs.dou.ua/companies/fuib/vacancies/11783/","Tags":["Design Patterns","SOLID","ASP.NET MVC"]}]},{"Name":"MoneyVeo","Vacancies":[{"PositionName":"FULL STACK C#/ASP.NET MVC DEVELOPER","Url":"https://jobs.dou.ua/companies/moneyveo/vacancies/41952/","Tags":["microservices","SOLID","ASP.NET MVC"]}]},{"Name":"EasyPay.UA","Vacancies":[{"PositionName":".NET WEB DEVELOPER","Url":"https://jobs.dou.ua/companies/easypay/vacancies/30065/","Tags":["ASP.NET Web API","ASP.NET MVC"]}]},{"Name":"Homsters","Vacancies":[{"PositionName":"MIDDLE .NET DEVELOPER","Url":"https://jobs.dou.ua/companies/homsters/vacancies/51236/","Tags":["ASP.NET MVC","AngularJS"]}]},{"Name":"SvitSoft","Vacancies":[{"PositionName":".NET DEVELOPER","Url":"https://jobs.dou.ua/companies/svitsoft/vacancies/42513/","Tags":["ASP.NET Web API","ASP.NET MVC","AngularJS"]}]},{"Name":"Onseo","Vacancies":[]}]